AUTHORS
CHANGELOG.rst
LICENSE
MANIFEST.in
README.rst
setup.py
PyDocX.egg-info/PKG-INFO
PyDocX.egg-info/SOURCES.txt
PyDocX.egg-info/dependency_links.txt
PyDocX.egg-info/entry_points.txt
PyDocX.egg-info/not-zip-safe
PyDocX.egg-info/top_level.txt
docs/Makefile
docs/conf.py
docs/conformance.rst
docs/development.rst
docs/enumerated_list_detection.rst
docs/export_mixins.rst
docs/extending.rst
docs/index.rst
docs/installation.rst
docs/release_notes.rst
docs/usage.rst
docs/_build/html/.buildinfo
docs/_build/html/conformance.html
docs/_build/html/development.html
docs/_build/html/enumerated_list_detection.html
docs/_build/html/export_mixins.html
docs/_build/html/extending.html
docs/_build/html/genindex.html
docs/_build/html/index.html
docs/_build/html/installation.html
docs/_build/html/objects.inv
docs/_build/html/release_notes.html
docs/_build/html/search.html
docs/_build/html/searchindex.js
docs/_build/html/usage.html
docs/_build/html/_sources/conformance.txt
docs/_build/html/_sources/development.txt
docs/_build/html/_sources/enumerated_list_detection.txt
docs/_build/html/_sources/export_mixins.txt
docs/_build/html/_sources/extending.txt
docs/_build/html/_sources/index.txt
docs/_build/html/_sources/installation.txt
docs/_build/html/_sources/release_notes.txt
docs/_build/html/_sources/usage.txt
docs/_build/html/_static/ajax-loader.gif
docs/_build/html/_static/basic.css
docs/_build/html/_static/comment-bright.png
docs/_build/html/_static/comment-close.png
docs/_build/html/_static/comment.png
docs/_build/html/_static/doctools.js
docs/_build/html/_static/down-pressed.png
docs/_build/html/_static/down.png
docs/_build/html/_static/file.png
docs/_build/html/_static/jquery-1.11.1.js
docs/_build/html/_static/jquery.js
docs/_build/html/_static/minus.png
docs/_build/html/_static/placeholder_do_not_delete
docs/_build/html/_static/plus.png
docs/_build/html/_static/pygments.css
docs/_build/html/_static/searchtools.js
docs/_build/html/_static/underscore-1.3.1.js
docs/_build/html/_static/underscore.js
docs/_build/html/_static/up-pressed.png
docs/_build/html/_static/up.png
docs/_build/html/_static/websupport.js
docs/_build/html/_static/css/badge_only.css
